README.md
mpsync.py
setup.cfg
setup.py
mpsync.egg-info/PKG-INFO
mpsync.egg-info/SOURCES.txt
mpsync.egg-info/dependency_links.txt
mpsync.egg-info/entry_points.txt
mpsync.egg-info/requires.txt
mpsync.egg-info/top_level.txt