Metadata-Version: 2.1
Name: mpsync
Version: 0.0.1
Summary: A synchronization tool for micro python boards
Home-page: https://github.com/Uhlo/mpsync
Author: Thilo Michael
Author-email: uhlomuhlo@gmail.com
License: UNKNOWN
Keywords: micropython,synchronization,serial,development
Platform: UNKNOWN
Classifier: Development Status :: 3 - Alpha
Classifier: Intended Audience :: Developers
Classifier: Topic :: Software Development :: Build Tools
Classifier: License :: OSI Approved :: MIT License
Classifier: Programming Language :: Python :: 3
Classifier: Programming Language :: Python :: 3.6
Classifier: Programming Language :: Python :: 3.7
Classifier: Programming Language :: Python :: 3.8
Classifier: Programming Language :: Python :: 3 :: Only
Requires-Python: >=3.6, <4
